geniebottle/__about__.py
geniebottle/__init__.py
geniebottle/applications.py
geniebottle/costcalculator.py
geniebottle/credentials.py
geniebottle/fastapi_generator.py
geniebottle/model_utils.py
geniebottle/models.py
geniebottle/module_loader.py
geniebottle/spellcasters.py
geniebottle/terminal_server.py
geniebottle/tokenizers.py
geniebottle/utils.py
geniebottle/decorators/__init__.py
geniebottle/decorators/agent_hint.py
geniebottle/decorators/bind_to_spellbook.py
geniebottle/decorators/class_spell.py
geniebottle/decorators/limit_cost.py
geniebottle/decorators/limit_cost_fields.py
geniebottle/decorators/type_check.py
geniebottle/helpers/__init__.py
geniebottle/helpers/agent.py
geniebottle/scrolls/__init__.py
geniebottle/scrolls/agent_scroll.py
geniebottle/scrolls/chat_scroll.py
geniebottle/scrolls/scroll.py
geniebottle/spellbooks/__init__.py
geniebottle/spellbooks/spellbook.py
geniebottle/spellbooks/agent/__init__.py
geniebottle/spellbooks/agent/spellbook.py
geniebottle/spellbooks/agent/spells.py
geniebottle/spellbooks/diffusers/__init__.py
geniebottle/spellbooks/diffusers/spellbook.py
geniebottle/spellbooks/diffusers/spells.py
geniebottle/spellbooks/editor/__init__.py
geniebottle/spellbooks/editor/spellbook.py
geniebottle/spellbooks/editor/spells.py
geniebottle/spellbooks/file/__init__.py
geniebottle/spellbooks/file/spellbook.py
geniebottle/spellbooks/file/spells.py
geniebottle/spellbooks/huggingface/spellbook.py
geniebottle/spellbooks/huggingface/spells.py
geniebottle/spellbooks/local/__init__.py
geniebottle/spellbooks/local/spellbook.py
geniebottle/spellbooks/local/spells.py
geniebottle/spellbooks/openai/__init__.py
geniebottle/spellbooks/openai/spellbook.py
geniebottle/spellbooks/openai/spells.py
geniebottle/spellbooks/stabilityai/__init__.py
geniebottle/spellbooks/stabilityai/spellbook.py
geniebottle/spellbooks/stabilityai/spells.py
geniebottle/static/terminal.html
geniebottle-0.0.3.dist-info/METADATA
geniebottle-0.0.3.dist-info/WHEEL
geniebottle-0.0.3.dist-info/licenses/LICENSE
geniebottle-0.0.3.dist-info/licenses/NOTICE
geniebottle-0.0.3.dist-info/RECORD
