Metadata-Version: 2.4
Name: geniebottle
Version: 0.0.3
Summary: Your personal AI server and Python package to do anything - like a magical genie
Project-URL: Documentation, https://github.com/jakemanger/geniebottle#readme
Project-URL: Issues, https://github.com/jakemanger/geniebottle/issues
Project-URL: Source, https://github.com/jakemanger/geniebottle
Author-email: Jake Manger <jake@merlinsbeard.ai>
License-Expression: MPL-2.0
License-File: LICENSE
License-File: NOTICE
Classifier: Development Status :: 4 - Beta
Classifier: Programming Language :: Python
Classifier: Programming Language :: Python :: 3.7
Classifier: Programming Language :: Python :: 3.8
Classifier: Programming Language :: Python :: 3.9
Classifier: Programming Language :: Python :: 3.10
Classifier: Programming Language :: Python :: 3.11
Classifier: Programming Language :: Python :: Implementation :: CPython
Classifier: Programming Language :: Python :: Implementation :: PyPy
Requires-Python: >=3.7
Requires-Dist: diffusers[torch]>=0.25.1
Requires-Dist: fastapi>=0.100.0
Requires-Dist: openai>=1.6.0
Requires-Dist: pillow>=8.3.2
Requires-Dist: pydantic>=2.0.0
Requires-Dist: pyobjc==9.0.1; platform_system == 'Darwin'
Requires-Dist: pyttsx3>=2.90
Requires-Dist: rich==13.7.0
Requires-Dist: stability-sdk>=0.8.4
Requires-Dist: tiktoken>=0.7.0
Requires-Dist: transformers==4.37.1
Requires-Dist: uvicorn>=0.24.0
Requires-Dist: websockets>=12.0
